statement_reader-0.2.4.dist-info/METADATA
statement_reader-0.2.4.dist-info/WHEEL
statement_reader-0.2.4.dist-info/entry_points.txt
statement_reader/__init__.py
statement_reader/models.py
statement_reader/parsers.py
statement_reader-0.2.4.dist-info/RECORD
