Metadata-Version: 2.1
Name: statement_reader
Version: 0.2.4
Summary: A Python library designed to parse bank operations from PDF statements
Author-Email: dkurchigin <kurchigin.dmitry@yandex.ru>
License: MIT
Classifier: Programming Language :: Python :: 3
Classifier: Programming Language :: Python
Classifier: Typing :: Typed
Classifier: Programming Language :: Python :: 3 :: Only
Classifier: Programming Language :: Python :: 3.10
Classifier: Programming Language :: Python :: 3.11
Classifier: Programming Language :: Python :: 3.12
Classifier: Programming Language :: Python :: 3.13
Project-URL: Homepage, https://gitverse.ru/dkurchigin/statement_reader
Project-URL: Documentation, https://statement-reader.dkurchigin.ru/
Project-URL: Source, https://gitverse.ru/dkurchigin/statement_reader
Requires-Python: >=3.10
Requires-Dist: pypdf>=5.8.0
Requires-Dist: pydantic>=2.11.7
